MANIFEST.in
README.rst
setup.py
PyOBEX/__init__.py
PyOBEX/client.py
PyOBEX/common.py
PyOBEX/headers.py
PyOBEX/requests.py
PyOBEX/responses.py
PyOBEX/server.py
bshare/__init__.py
bshare/bshare.py
bshare/default_addr
bshare.egg-info/PKG-INFO
bshare.egg-info/SOURCES.txt
bshare.egg-info/dependency_links.txt
bshare.egg-info/entry_points.txt
bshare.egg-info/not-zip-safe
bshare.egg-info/requires.txt
bshare.egg-info/top_level.txt