Metadata-Version: 1.1
Name: bshare
Version: 1.0.0
Summary: A command line bluetooth file sharing application for Linux.
Home-page: https://github.com/nikhilkumarsingh/bshare
Author: Nikhil Kumar Singh
Author-email: nikhilksingh97@gmail.com
License: MIT
Keywords: bluetooth file sharer
Platform: UNKNOWN
Classifier: Development Status :: 4 - Beta
Classifier: License :: OSI Approved :: MIT License
Classifier: Programming Language :: Python
Classifier: Programming Language :: Python :: 2
Classifier: Programming Language :: Python :: 2.6
Classifier: Programming Language :: Python :: 2.7
Classifier: Programming Language :: Python :: 3
Classifier: Programming Language :: Python :: 3.3
Classifier: Programming Language :: Python :: 3.4
Classifier: Programming Language :: Python :: 3.5
Classifier: Programming Language :: Python :: 3.6
